[
  {
    "iso": "CHE",
    "value": 5961
  },
  {
    "iso": "NOR",
    "value": 5846
  },
  {
    "iso": "LUX",
    "value": 5296
  },
  {
    "iso": "DNK",
    "value": 3939
  },
  {
    "iso": "SWE",
    "value": 3729
  },
  {
    "iso": "AUT",
    "value": 3464
  },
  {
    "iso": "GBR",
    "value": 3382
  },
  {
    "iso": "FIN",
    "value": 3358
  },
  {
    "iso": "FRA",
    "value": 3229
  },
  {
    "iso": "IRL",
    "value": 3215
  },
  {
    "iso": "ISL",
    "value": 3090
  },
  {
    "iso": "DEU",
    "value": 3073
  },
  {
    "iso": "BEL",
    "value": 3060
  },
  {
    "iso": "NLD",
    "value": 3029
  },
  {
    "iso": "CYP",
    "value": 2531
  },
  {
    "iso": "ITA",
    "value": 2520
  },
  {
    "iso": "ESP",
    "value": 2315
  },
  {
    "iso": "MLT",
    "value": 1964
  },
  {
    "iso": "SVN",
    "value": 1675
  },
  {
    "iso": "PRT",
    "value": 1474
  },
  {
    "iso": "EST",
    "value": 1370
  },
  {
    "iso": "GRC",
    "value": 1293
  },
  {
    "iso": "CZE",
    "value": 1104
  },
  {
    "iso": "SVK",
    "value": 964
  },
  {
    "iso": "LVA",
    "value": 960
  },
  {
    "iso": "LTU",
    "value": 902
  },
  {
    "iso": "POL",
    "value": 872
  },
  {
    "iso": "HRV",
    "value": 828
  },
  {
    "iso": "HUN",
    "value": 694
  },
  {
    "iso": "BGR",
    "value": 574
  },
  {
    "iso": "SRB",
    "value": 435
  },
  {
    "iso": "ROU",
    "value": 368
  },
  {
    "iso": "MKD",
    "value": 356
  }
]